tqsdk_sm/__init__.py
tqsdk_sm-1.0.4.dist-info/METADATA
tqsdk_sm-1.0.4.dist-info/WHEEL
tqsdk_sm-1.0.4.dist-info/top_level.txt
tqsdk_sm-1.0.4.dist-info/RECORD
