Metadata-Version: 2.1
Name: tqsdk-sm
Version: 1.0.4
Summary: TianQin SDK - sm lib
Home-page: https://www.shinnytech.com/tqsdk
Author: TianQin
Author-email: tianqincn@gmail.com
License: UNKNOWN
Platform: UNKNOWN
Requires-Python: >=3
